sensorhub/__init__.py
sensorhub/hub.py
sensorhub-2.0.3.dist-info/LICENSE
sensorhub-2.0.3.dist-info/METADATA
sensorhub-2.0.3.dist-info/WHEEL
sensorhub-2.0.3.dist-info/top_level.txt
sensorhub-2.0.3.dist-info/RECORD
