Metadata-Version: 2.1
Name: sensorhub
Version: 2.0.3
Summary: A simple library to use with the DockerPi SensorHub (EP-0106)
Home-page: https://github.com/MGough/sensorhub
Author: Merlin Gough
Author-email: goughmerlin@gmail.com
License: UNKNOWN
Platform: UNKNOWN
Classifier: Programming Language :: Python :: 3
Classifier: License :: OSI Approved :: MIT License
Classifier: Operating System :: OS Independent
Requires-Python: >=3.7
License-File: LICENSE
Requires-Dist: smbus2 (>=0.3.0)
